bilitool/__init__.py
bilitool/cli.py
bilitool/authenticate/__init__.py
bilitool/authenticate/wbi_sign.py
bilitool/controller/__init__.py
bilitool/controller/download_controller.py
bilitool/controller/feed_controller.py
bilitool/controller/login_controller.py
bilitool/controller/upload_controller.py
bilitool/download/__init__.py
bilitool/download/bili_download.py
bilitool/feed/__init__.py
bilitool/feed/bili_live_list.py
bilitool/feed/bili_video_list.py
bilitool/login/__init__.py
bilitool/login/check_bili_login.py
bilitool/login/login_bili.py
bilitool/login/logout_bili.py
bilitool/model/__init__.py
bilitool/model/config.json
bilitool/model/model.py
bilitool/upload/__init__.py
bilitool/upload/bili_upload.py
bilitool/utils/__init__.py
bilitool/utils/check_format.py
bilitool/utils/get_ip_info.py
bilitool/utils/parse_cookies.py
bilitool/utils/parse_yaml.py
bilitool-0.1.3.dist-info/METADATA
bilitool-0.1.3.dist-info/WHEEL
bilitool-0.1.3.dist-info/entry_points.txt
bilitool-0.1.3.dist-info/licenses/LICENSE
bilitool-0.1.3.dist-info/RECORD
