Metadata-Version: 2.4
Name: bilitool
Version: 0.1.3
Summary: The Python toolkit package and cli designed for interaction with Bilibili
Project-URL: Homepage, https://github.com/timerring/bilitool
Author: timerring
License: MIT License
License-File: LICENSE
Classifier: License :: OSI Approved :: MIT License
Classifier: Operating System :: OS Independent
Classifier: Programming Language :: Python :: 3
Requires-Python: >=3.9
Requires-Dist: pillow>=5.2.0
Requires-Dist: pyyaml>=6.0.2
Requires-Dist: qrcode>=8.0
Requires-Dist: requests>=2.32.3
Requires-Dist: tqdm>=4.67.1
